json2xml/__init__.py
json2xml/cli.py
json2xml/dicttoxml.py
json2xml/dicttoxml_fast.py
json2xml/json2xml.py
json2xml/utils.py
json2xml-6.0.2.dist-info/licenses/AUTHORS.rst
json2xml-6.0.2.dist-info/licenses/LICENSE
json2xml-6.0.2.dist-info/METADATA
json2xml-6.0.2.dist-info/WHEEL
json2xml-6.0.2.dist-info/entry_points.txt
json2xml-6.0.2.dist-info/top_level.txt
json2xml-6.0.2.dist-info/RECORD
