Metadata-Version: 2.4
Name: json2xml
Version: 6.0.2
Summary: Simple Python Library to convert JSON to XML
Author-email: Vinit Kumar <mail@vinitkumar.me>
License: Apache Software License 2.0
Project-URL: Homepage, https://github.com/vinitkumar/json2xml
Keywords: json2xml
Classifier: Development Status :: 6 - Mature
Classifier: Intended Audience :: Developers
Classifier: License :: OSI Approved :: Apache Software License
Classifier: Natural Language :: English
Classifier: Programming Language :: Python :: 3.10
Classifier: Programming Language :: Python :: 3.11
Classifier: Programming Language :: Python :: 3.12
Classifier: Programming Language :: Python :: 3.13
Classifier: Programming Language :: Python :: 3.14
Classifier: Programming Language :: Python :: Implementation :: CPython
Classifier: Programming Language :: Python :: Implementation :: PyPy
Classifier: Topic :: Software Development :: Libraries :: Python Modules
Requires-Python: >=3.10
License-File: LICENSE
License-File: AUTHORS.rst
Requires-Dist: defusedxml
Requires-Dist: urllib3
Requires-Dist: xmltodict>=0.12.0
Requires-Dist: pytest
Requires-Dist: pytest-cov
Requires-Dist: coverage
Requires-Dist: setuptools
Provides-Extra: test
Requires-Dist: pytest>=8.4.1; extra == "test"
Provides-Extra: fast
Requires-Dist: json2xml-rs>=0.1.0; extra == "fast"
Dynamic: license-file
